[{"id":7,"title":"another tst","creating_time":"0001-01-01T00:00:00Z","editing_time":"0001-01-01T00:00:00Z","content":"no content"},{"id":3,"title":"testaa3","creating_time":"0001-01-01T00:00:00Z","editing_time":"0001-01-01T00:00:00Z","content":"no content"},{"id":4,"title":"TESTING","creating_time":"0001-01-01T00:00:00Z","editing_time":"0001-01-01T00:00:00Z","content":"no content CHANGED"},{"id":6,"title":"adding","creating_time":"0001-01-01T00:00:00Z","editing_time":"0001-01-01T00:00:00Z","content":"no content CHANGED"},{"id":9,"title":"another tst","creating_time":"0001-01-01T00:00:00Z","editing_time":"0001-01-01T00:00:00Z","content":"no content"},{"id":10,"title":"adding","creating_time":"0001-01-01T00:00:00Z","editing_time":"0001-01-01T00:00:00Z","content":"no content CHANGED"},{"id":11,"title":"another tst","creating_time":"2025-01-25T22:24:38.859323349+04:00","editing_time":"2025-01-25T22:24:38.859323349+04:00","content":"no content"}]